MANIFEST.in
README.rst
setup.py
compile/CMakeLists.txt
compile/demo/.gitignore
compile/demo/CMakeLists.txt
compile/demo/classification/criteo_ctr/README.rst
compile/demo/classification/criteo_ctr/run_demo_ctr.py
compile/demo/classification/criteo_ctr/run_demo_ctr.sh
compile/demo/classification/criteo_ctr/small_test.txt
compile/demo/classification/criteo_ctr/small_train.txt
compile/demo/classification/higgs/README.rst
compile/demo/classification/higgs/higgs-test.csv
compile/demo/classification/higgs/higgs-train.csv
compile/demo/classification/higgs/run_higgs.py
compile/demo/classification/higgs/run_higgs.sh
compile/demo/classification/mushroom/README.rst
compile/demo/classification/mushroom/agaricus_test.txt
compile/demo/classification/mushroom/agaricus_train.txt
compile/demo/classification/mushroom/run_demo_mushroom.py
compile/demo/classification/mushroom/run_demo_mushroom.sh
compile/demo/classification/scikit_learn_demo/README.dst
compile/demo/classification/scikit_learn_demo/example_FFM_criteo.py
compile/demo/classification/scikit_learn_demo/example_FM_wine.py
compile/demo/classification/scikit_learn_demo/example_LR_iris.py
compile/demo/classification/titanic/README.rst
compile/demo/classification/titanic/run_demo_titanic.py
compile/demo/classification/titanic/run_demo_titanic.sh
compile/demo/classification/titanic/titanic_test.txt
compile/demo/classification/titanic/titanic_train.txt
compile/demo/regression/house_price/README.rst
compile/demo/regression/house_price/house_price_test.txt
compile/demo/regression/house_price/house_price_train.txt
compile/demo/regression/house_price/run_demo_house_price.py
compile/demo/regression/house_price/run_demo_house_price.sh
compile/demo/regression/house_price/run_house_no_cv.py
compile/demo/regression/house_price/run_house_no_cv.sh
compile/gtest/CHANGES
compile/gtest/CMakeLists.txt
compile/gtest/CONTRIBUTORS
compile/gtest/LICENSE
compile/gtest/Makefile
compile/gtest/Makefile.am
compile/gtest/Makefile.in
compile/gtest/README
xlearn.egg-info/PKG-INFO
xlearn.egg-info/SOURCES.txt
xlearn.egg-info/dependency_links.txt
xlearn.egg-info/not-zip-safe
xlearn.egg-info/top_level.txt