Metadata-Version: 1.1
Name: xlearn
Version: 0.40a1
Summary: xLearn Python Package
Home-page: https://github.com/aksnzhy/xlearn
Author: Chao Ma
Author-email: mctt90@gmail.com
License: Apache-2.0
Platform: UNKNOWN
Classifier: License :: OSI Approved :: Apache Software License
